flask_secure_keygen/__init__.py
flask_secure_keygen/keygen.py
flask_secure_keygen/utils.py
tests/__init__.py
tests/test_keygen.py
FlaskSecureKeyGen-0.1.0.dist-info/LICENSE
FlaskSecureKeyGen-0.1.0.dist-info/METADATA
FlaskSecureKeyGen-0.1.0.dist-info/WHEEL
FlaskSecureKeyGen-0.1.0.dist-info/top_level.txt
FlaskSecureKeyGen-0.1.0.dist-info/RECORD
