Metadata-Version: 2.2
Name: FlaskSecureKeyGen
Version: 0.1.0
Summary: A library to generate secure random secret keys for Flask apps.
Home-page: https://github.com/ChAbdulWahhab/FlaskSecureKeyGen
Author: Ch. Abdul Wahab
Author-email: ch.abdul.wahab310@gmail.com
Classifier: Programming Language :: Python :: 3
Classifier: License :: OSI Approved :: MIT License
Classifier: Operating System :: OS Independent
Requires-Python: >=3.6
License-File: LICENSE
Dynamic: author
Dynamic: author-email
Dynamic: classifier
Dynamic: description
Dynamic: description-content-type
Dynamic: home-page
Dynamic: requires-python
Dynamic: summary
